calcat.py
calcat-1.0.1.dist-info/LICENSE
calcat-1.0.1.dist-info/METADATA
calcat-1.0.1.dist-info/WHEEL
calcat-1.0.1.dist-info/top_level.txt
calcat-1.0.1.dist-info/RECORD
