Metadata-Version: 2.1
Name: calcat
Version: 1.0.1
Summary: A Python package for basic arithmetic operations.
Home-page: https://github.com/TuringCollegeSubmissions/athiel-DWWP.1.5
Author: Agnieszka Thiel
Author-email: Agnieszka Thiel <ag.thiel.arc@gmail.com>
License: MIT
Project-URL: homepage, https://github.com/TuringCollegeSubmissions/athiel-DWWP.1.5
Project-URL: bugtracker, https://github.com/TuringCollegeSubmissions/athiel-DWWP.1.5/issues
Classifier: Programming Language :: Python :: 3
Classifier: License :: OSI Approved :: MIT License
Classifier: Operating System :: OS Independent
Requires-Python: >=3.9.5
License-File: LICENSE
Provides-Extra: dev
Requires-Dist: pytest >=7.4.3 ; extra == 'dev'
